{
    "debug_cores": [
        {
            "name": "la0",
            "type": "la",
            "uuid": "5197458aa2f9411db857749376f13911",
            "trigin_en": false,
            "trigout_en": false,
            "auto_inserted": true,
            "capture_control": false,
            "data_depth": 4096,
            "input_pipeline": 1,
            "probes": [
                {
                    "name": "ddr_reset_sequencer_inst/o_ddr_axi_rstn",
                    "width": 1,
                    "probe_type": 1
                },
                {
                    "name": "ddr_reset_sequencer_inst/o_ddr_init_done",
                    "width": 1,
                    "probe_type": 1
                },
                {
                    "name": "ddr_reset_sequencer_inst/o_ddr_cfg_seq_start",
                    "width": 1,
                    "probe_type": 1
                },
                {
                    "name": "ddr_reset_sequencer_inst/qCntnRST",
                    "width": 1,
                    "probe_type": 1
                },
                {
                    "name": "ddr_reset_sequencer_inst/iSRST",
                    "width": 1,
                    "probe_type": 1
                },
                {
                    "name": "ddr_reset_sequencer_inst/cnt_start",
                    "width": 8,
                    "probe_type": 1
                },
                {
                    "name": "ddr_reset_sequencer_inst/rstn_dly",
                    "width": 5,
                    "probe_type": 1
                },
                {
                    "name": "ddr_reset_sequencer_inst/qCntMaxCke",
                    "width": 1,
                    "probe_type": 1
                },
                {
                    "name": "ddr_reset_sequencer_inst/o_ddr_cfg_seq_rst",
                    "width": 1,
                    "probe_type": 1
                }
            ]
        }
    ],
    "connections": [
        {
            "command": "add_ports",
            "id": 1,
            "args": {
                "netlist": "MTopFmbTester",
                "ports": [
                    {
                        "name": "jtag_inst2_CAPTURE",
                        "dir": "in",
                        "width": 1
                    },
                    {
                        "name": "jtag_inst2_DRCK",
                        "dir": "in",
                        "width": 1
                    },
                    {
                        "name": "jtag_inst2_RESET",
                        "dir": "in",
                        "width": 1
                    },
                    {
                        "name": "jtag_inst2_RUNTEST",
                        "dir": "in",
                        "width": 1
                    },
                    {
                        "name": "jtag_inst2_SEL",
                        "dir": "in",
                        "width": 1
                    },
                    {
                        "name": "jtag_inst2_SHIFT",
                        "dir": "in",
                        "width": 1
                    },
                    {
                        "name": "jtag_inst2_TCK",
                        "dir": "in",
                        "width": 1
                    },
                    {
                        "name": "jtag_inst2_TDI",
                        "dir": "in",
                        "width": 1
                    },
                    {
                        "name": "jtag_inst2_TMS",
                        "dir": "in",
                        "width": 1
                    },
                    {
                        "name": "jtag_inst2_UPDATE",
                        "dir": "in",
                        "width": 1
                    },
                    {
                        "name": "jtag_inst2_TDO",
                        "dir": "out",
                        "width": 1
                    }
                ]
            }
        },
        {
            "command": "instantiate",
            "netlist": "edb_top",
            "id": 2,
            "instance": "edb_top_inst"
        },
        {
            "command": "connect",
            "id": 3,
            "args": {
                "instance": "edb_top_inst",
                "ports": [
                    {
                        "name": "bscan_CAPTURE",
                        "net": "jtag_inst2_CAPTURE"
                    },
                    {
                        "name": "bscan_DRCK",
                        "net": "jtag_inst2_DRCK"
                    },
                    {
                        "name": "bscan_RESET",
                        "net": "jtag_inst2_RESET"
                    },
                    {
                        "name": "bscan_RUNTEST",
                        "net": "jtag_inst2_RUNTEST"
                    },
                    {
                        "name": "bscan_SEL",
                        "net": "jtag_inst2_SEL"
                    },
                    {
                        "name": "bscan_SHIFT",
                        "net": "jtag_inst2_SHIFT"
                    },
                    {
                        "name": "bscan_TCK",
                        "net": "jtag_inst2_TCK"
                    },
                    {
                        "name": "bscan_TDI",
                        "net": "jtag_inst2_TDI"
                    },
                    {
                        "name": "bscan_TMS",
                        "net": "jtag_inst2_TMS"
                    },
                    {
                        "name": "bscan_UPDATE",
                        "net": "jtag_inst2_UPDATE"
                    },
                    {
                        "name": "bscan_TDO",
                        "net": "jtag_inst2_TDO"
                    },
                    {
                        "name": "la0_clk",
                        "net": "iSCLK",
                        "path": []
                    },
                    {
                        "name": "la0_probe0",
                        "net": "o_ddr_axi_rstn",
                        "path": [
                            "ddr_reset_sequencer_inst"
                        ]
                    },
                    {
                        "name": "la0_probe1",
                        "net": "o_ddr_init_done",
                        "path": [
                            "ddr_reset_sequencer_inst"
                        ]
                    },
                    {
                        "name": "la0_probe2",
                        "net": "o_ddr_cfg_seq_start",
                        "path": [
                            "ddr_reset_sequencer_inst"
                        ]
                    },
                    {
                        "name": "la0_probe3",
                        "net": "qCntnRST",
                        "path": [
                            "ddr_reset_sequencer_inst"
                        ]
                    },
                    {
                        "name": "la0_probe4",
                        "net": "iSRST",
                        "path": [
                            "ddr_reset_sequencer_inst"
                        ]
                    },
                    {
                        "name": "la0_probe5[0]",
                        "net": "cnt_start[0]",
                        "path": [
                            "ddr_reset_sequencer_inst"
                        ]
                    },
                    {
                        "name": "la0_probe5[1]",
                        "net": "cnt_start[1]",
                        "path": [
                            "ddr_reset_sequencer_inst"
                        ]
                    },
                    {
                        "name": "la0_probe5[2]",
                        "net": "cnt_start[2]",
                        "path": [
                            "ddr_reset_sequencer_inst"
                        ]
                    },
                    {
                        "name": "la0_probe5[3]",
                        "net": "cnt_start[3]",
                        "path": [
                            "ddr_reset_sequencer_inst"
                        ]
                    },
                    {
                        "name": "la0_probe5[4]",
                        "net": "cnt_start[4]",
                        "path": [
                            "ddr_reset_sequencer_inst"
                        ]
                    },
                    {
                        "name": "la0_probe5[5]",
                        "net": "cnt_start[5]",
                        "path": [
                            "ddr_reset_sequencer_inst"
                        ]
                    },
                    {
                        "name": "la0_probe5[6]",
                        "net": "cnt_start[6]",
                        "path": [
                            "ddr_reset_sequencer_inst"
                        ]
                    },
                    {
                        "name": "la0_probe5[7]",
                        "net": "cnt_start[7]",
                        "path": [
                            "ddr_reset_sequencer_inst"
                        ]
                    },
                    {
                        "name": "la0_probe6[0]",
                        "net": "rstn_dly[0]",
                        "path": [
                            "ddr_reset_sequencer_inst"
                        ]
                    },
                    {
                        "name": "la0_probe6[1]",
                        "net": "rstn_dly[1]",
                        "path": [
                            "ddr_reset_sequencer_inst"
                        ]
                    },
                    {
                        "name": "la0_probe6[2]",
                        "net": "rstn_dly[2]",
                        "path": [
                            "ddr_reset_sequencer_inst"
                        ]
                    },
                    {
                        "name": "la0_probe6[3]",
                        "net": "rstn_dly[3]",
                        "path": [
                            "ddr_reset_sequencer_inst"
                        ]
                    },
                    {
                        "name": "la0_probe6[4]",
                        "net": "rstn_dly[4]",
                        "path": [
                            "ddr_reset_sequencer_inst"
                        ]
                    },
                    {
                        "name": "la0_probe7",
                        "net": "qCntMaxCke",
                        "path": [
                            "ddr_reset_sequencer_inst"
                        ]
                    },
                    {
                        "name": "la0_probe8",
                        "net": "o_ddr_cfg_seq_rst",
                        "path": [
                            "ddr_reset_sequencer_inst"
                        ]
                    }
                ]
            }
        }
    ],
    "vdbs": [
        {
            "file": "debug_top.post.vdb",
            "instance": "edb_top_inst"
        }
    ],
    "session": {
        "wizard": {
            "data_depth": 4096,
            "capture_control": false,
            "selected_nets": [
                {
                    "name": "o_ddr_axi_rstn",
                    "width": 1,
                    "clk_domain": "iSCLK",
                    "selected_probe_type": "DATA AND TRIGGER",
                    "child": [],
                    "path": [
                        "ddr_reset_sequencer_inst"
                    ]
                },
                {
                    "name": "o_ddr_init_done",
                    "width": 1,
                    "clk_domain": "iSCLK",
                    "selected_probe_type": "DATA AND TRIGGER",
                    "child": [],
                    "path": [
                        "ddr_reset_sequencer_inst"
                    ]
                },
                {
                    "name": "o_ddr_cfg_seq_start",
                    "width": 1,
                    "clk_domain": "iSCLK",
                    "selected_probe_type": "DATA AND TRIGGER",
                    "child": [],
                    "path": [
                        "ddr_reset_sequencer_inst"
                    ]
                },
                {
                    "name": "qCntnRST",
                    "width": 1,
                    "clk_domain": "iSCLK",
                    "selected_probe_type": "DATA AND TRIGGER",
                    "child": [],
                    "path": [
                        "ddr_reset_sequencer_inst"
                    ]
                },
                {
                    "name": "iSRST",
                    "width": 1,
                    "clk_domain": "iSCLK",
                    "selected_probe_type": "DATA AND TRIGGER",
                    "child": [],
                    "path": [
                        "ddr_reset_sequencer_inst"
                    ]
                },
                {
                    "name": "cnt_start",
                    "width": 8,
                    "clk_domain": "iSCLK",
                    "selected_probe_type": "DATA AND TRIGGER",
                    "child": [],
                    "path": [
                        "ddr_reset_sequencer_inst"
                    ],
                    "net_idx_left": 7,
                    "net_idx_right": 0
                },
                {
                    "name": "rstn_dly",
                    "width": 5,
                    "clk_domain": "iSCLK",
                    "selected_probe_type": "DATA AND TRIGGER",
                    "child": [],
                    "path": [
                        "ddr_reset_sequencer_inst"
                    ],
                    "net_idx_left": 4,
                    "net_idx_right": 0
                },
                {
                    "name": "qCntMaxCke",
                    "width": 1,
                    "clk_domain": "iSCLK",
                    "selected_probe_type": "DATA AND TRIGGER",
                    "child": [],
                    "path": [
                        "ddr_reset_sequencer_inst"
                    ]
                },
                {
                    "name": "o_ddr_cfg_seq_rst",
                    "width": 1,
                    "clk_domain": "iSCLK",
                    "selected_probe_type": "DATA AND TRIGGER",
                    "child": [],
                    "path": [
                        "ddr_reset_sequencer_inst"
                    ]
                }
            ],
            "top_module": "MTopFmbTester",
            "db_checksum": "ba5fce12098a2c03e7bae2e9a172d1842464edfca8e284870b3519e987537970",
            "src": "elaborate",
            "jtag_user": "USER2",
            "input_pipeline": 1
        }
    }
}