<?xml version="1.0" encoding="UTF-8"?>
<efxpt:design_db name="K5Stack10_MIDI" device_def="T20Q144" location="/home/kimura/workspace/ProjectFolder/Efinix/Trion/K5Stack10_MIDI" version="2023.1.150.6.14" db_version="20231999" last_change_date="Thu Jan  4 18:46:38 2024" xmlns:efxpt="http://www.efinixinc.com/peri_design_db" xmlns:xsi="http://www.w3.org/2001/XMLSchema-instance" xsi:schemaLocation="http://www.efinixinc.com/peri_design_db peri_design_db.xsd ">
    <efxpt:device_info>
        <efxpt:iobank_info>
            <efxpt:iobank name="1A" iostd="3.3 V LVTTL / LVCMOS"/>
            <efxpt:iobank name="1B" iostd="3.3 V LVTTL / LVCMOS"/>
            <efxpt:iobank name="1C_1D" iostd="3.3 V LVTTL / LVCMOS"/>
            <efxpt:iobank name="1E" iostd="3.3 V LVTTL / LVCMOS"/>
            <efxpt:iobank name="3A" iostd="3.3 V LVTTL / LVCMOS"/>
            <efxpt:iobank name="3B_3C" iostd="3.3 V LVTTL / LVCMOS"/>
            <efxpt:iobank name="3D" iostd="3.3 V LVTTL / LVCMOS"/>
            <efxpt:iobank name="3E" iostd="3.3 V LVTTL / LVCMOS"/>
            <efxpt:iobank name="4A" iostd="3.3 V LVTTL / LVCMOS"/>
            <efxpt:iobank name="4B" iostd="3.3 V LVTTL / LVCMOS"/>
            <efxpt:iobank name="BR" iostd="1.2 V"/>
            <efxpt:iobank name="TL" iostd="1.2 V"/>
            <efxpt:iobank name="TR" iostd="1.2 V"/>
        </efxpt:iobank_info>
        <efxpt:ctrl_info>
            <efxpt:ctrl name="cfg" ctrl_def="CONFIG_CTRL0" clock_name="" is_clk_invert="false" cbsel_bus_name="cfg_CBSEL" config_ctrl_name="cfg_CONFIG" ena_capture_name="cfg_ENA" error_status_name="cfg_ERROR" um_signal_status_name="cfg_USR_STATUS" is_remote_update_enable="false" is_user_mode_enable="false"/>
        </efxpt:ctrl_info>
    </efxpt:device_info>
    <efxpt:gpio_info device_def="T20Q144">
        <efxpt:gpio name="iOSC_IN" gpio_def="GPIOR_157" mode="input" bus_name="" is_lvds_gpio="false" io_standard="3.3 V LVTTL / LVCMOS">
            <efxpt:input_config name="iOSC_IN" name_ddio_lo="" conn_type="pll_clkin" is_register="false" clock_name="" is_clock_inverted="false" pull_option="none" is_schmitt_trigger="false" ddio_type="none"/>
        </efxpt:gpio>
        <efxpt:gpio name="iUSB_RX" gpio_def="GPIOB_RXP07" mode="input" bus_name="" is_lvds_gpio="true" io_standard="3.3 V LVTTL / LVCMOS">
            <efxpt:input_config name="iUSB_RX" name_ddio_lo="" conn_type="normal" is_register="false" clock_name="" is_clock_inverted="false" pull_option="weak pullup" is_schmitt_trigger="false" ddio_type="none"/>
        </efxpt:gpio>
        <efxpt:gpio name="ioGPIOB[0]" gpio_def="GPIOB_TXP00" mode="inout" bus_name="ioGPIOB" is_lvds_gpio="true" io_standard="3.3 V LVTTL / LVCMOS">
            <efxpt:input_config name="ioGPIOB_I[0]" name_ddio_lo="" conn_type="normal" is_register="false" clock_name="" is_clock_inverted="false" pull_option="weak pullup" is_schmitt_trigger="false" ddio_type="none"/>
            <efxpt:output_config name="ioGPIOB_O[0]" name_ddio_lo="" register_option="none" clock_name="" is_clock_inverted="false" is_slew_rate="false" tied_option="none" ddio_type="none" drive_strength="1"/>
            <efxpt:output_enable_config name="ioGPIOB_OE[0]" is_register="false" clock_name="" is_clock_inverted="false"/>
        </efxpt:gpio>
        <efxpt:gpio name="ioGPIOB[10]" gpio_def="GPIOB_TXP11" mode="inout" bus_name="ioGPIOB" is_lvds_gpio="true" io_standard="3.3 V LVTTL / LVCMOS">
            <efxpt:input_config name="ioGPIOB_I[10]" name_ddio_lo="" conn_type="normal" is_register="false" clock_name="" is_clock_inverted="false" pull_option="weak pullup" is_schmitt_trigger="false" ddio_type="none"/>
            <efxpt:output_config name="ioGPIOB_O[10]" name_ddio_lo="" register_option="none" clock_name="" is_clock_inverted="false" is_slew_rate="false" tied_option="none" ddio_type="none" drive_strength="1"/>
            <efxpt:output_enable_config name="ioGPIOB_OE[10]" is_register="false" clock_name="" is_clock_inverted="false"/>
        </efxpt:gpio>
        <efxpt:gpio name="ioGPIOB[11]" gpio_def="GPIOB_TXN11" mode="inout" bus_name="ioGPIOB" is_lvds_gpio="true" io_standard="3.3 V LVTTL / LVCMOS">
            <efxpt:input_config name="ioGPIOB_I[11]" name_ddio_lo="" conn_type="normal" is_register="false" clock_name="" is_clock_inverted="false" pull_option="weak pullup" is_schmitt_trigger="false" ddio_type="none"/>
            <efxpt:output_config name="ioGPIOB_O[11]" name_ddio_lo="" register_option="none" clock_name="" is_clock_inverted="false" is_slew_rate="false" tied_option="none" ddio_type="none" drive_strength="1"/>
            <efxpt:output_enable_config name="ioGPIOB_OE[11]" is_register="false" clock_name="" is_clock_inverted="false"/>
        </efxpt:gpio>
        <efxpt:gpio name="ioGPIOB[12]" gpio_def="GPIOB_RXP00" mode="inout" bus_name="ioGPIOB" is_lvds_gpio="true" io_standard="3.3 V LVTTL / LVCMOS">
            <efxpt:input_config name="ioGPIOB_I[12]" name_ddio_lo="" conn_type="normal" is_register="false" clock_name="" is_clock_inverted="false" pull_option="weak pullup" is_schmitt_trigger="false" ddio_type="none"/>
            <efxpt:output_config name="ioGPIOB_O[12]" name_ddio_lo="" register_option="none" clock_name="" is_clock_inverted="false" is_slew_rate="false" tied_option="none" ddio_type="none" drive_strength="1"/>
            <efxpt:output_enable_config name="ioGPIOB_OE[12]" is_register="false" clock_name="" is_clock_inverted="false"/>
        </efxpt:gpio>
        <efxpt:gpio name="ioGPIOB[13]" gpio_def="GPIOB_RXN00" mode="inout" bus_name="ioGPIOB" is_lvds_gpio="true" io_standard="3.3 V LVTTL / LVCMOS">
            <efxpt:input_config name="ioGPIOB_I[13]" name_ddio_lo="" conn_type="normal" is_register="false" clock_name="" is_clock_inverted="false" pull_option="weak pullup" is_schmitt_trigger="false" ddio_type="none"/>
            <efxpt:output_config name="ioGPIOB_O[13]" name_ddio_lo="" register_option="none" clock_name="" is_clock_inverted="false" is_slew_rate="false" tied_option="none" ddio_type="none" drive_strength="1"/>
            <efxpt:output_enable_config name="ioGPIOB_OE[13]" is_register="false" clock_name="" is_clock_inverted="false"/>
        </efxpt:gpio>
        <efxpt:gpio name="ioGPIOB[14]" gpio_def="GPIOB_RXP02" mode="inout" bus_name="ioGPIOB" is_lvds_gpio="true" io_standard="3.3 V LVTTL / LVCMOS">
            <efxpt:input_config name="ioGPIOB_I[14]" name_ddio_lo="" conn_type="normal" is_register="false" clock_name="" is_clock_inverted="false" pull_option="weak pullup" is_schmitt_trigger="false" ddio_type="none"/>
            <efxpt:output_config name="ioGPIOB_O[14]" name_ddio_lo="" register_option="none" clock_name="" is_clock_inverted="false" is_slew_rate="false" tied_option="none" ddio_type="none" drive_strength="1"/>
            <efxpt:output_enable_config name="ioGPIOB_OE[14]" is_register="false" clock_name="" is_clock_inverted="false"/>
        </efxpt:gpio>
        <efxpt:gpio name="ioGPIOB[15]" gpio_def="GPIOB_RXN02" mode="inout" bus_name="ioGPIOB" is_lvds_gpio="true" io_standard="3.3 V LVTTL / LVCMOS">
            <efxpt:input_config name="ioGPIOB_I[15]" name_ddio_lo="" conn_type="normal" is_register="false" clock_name="" is_clock_inverted="false" pull_option="weak pullup" is_schmitt_trigger="false" ddio_type="none"/>
            <efxpt:output_config name="ioGPIOB_O[15]" name_ddio_lo="" register_option="none" clock_name="" is_clock_inverted="false" is_slew_rate="false" tied_option="none" ddio_type="none" drive_strength="1"/>
            <efxpt:output_enable_config name="ioGPIOB_OE[15]" is_register="false" clock_name="" is_clock_inverted="false"/>
        </efxpt:gpio>
        <efxpt:gpio name="ioGPIOB[16]" gpio_def="GPIOB_RXN03" mode="inout" bus_name="ioGPIOB" is_lvds_gpio="true" io_standard="3.3 V LVTTL / LVCMOS">
            <efxpt:input_config name="ioGPIOB_I[16]" name_ddio_lo="" conn_type="normal" is_register="false" clock_name="" is_clock_inverted="false" pull_option="weak pullup" is_schmitt_trigger="false" ddio_type="none"/>
            <efxpt:output_config name="ioGPIOB_O[16]" name_ddio_lo="" register_option="none" clock_name="" is_clock_inverted="false" is_slew_rate="false" tied_option="none" ddio_type="none" drive_strength="1"/>
            <efxpt:output_enable_config name="ioGPIOB_OE[16]" is_register="false" clock_name="" is_clock_inverted="false"/>
        </efxpt:gpio>
        <efxpt:gpio name="ioGPIOB[17]" gpio_def="GPIOB_RXP03" mode="inout" bus_name="ioGPIOB" is_lvds_gpio="true" io_standard="3.3 V LVTTL / LVCMOS">
            <efxpt:input_config name="ioGPIOB_I[17]" name_ddio_lo="" conn_type="normal" is_register="false" clock_name="" is_clock_inverted="false" pull_option="weak pullup" is_schmitt_trigger="false" ddio_type="none"/>
            <efxpt:output_config name="ioGPIOB_O[17]" name_ddio_lo="" register_option="none" clock_name="" is_clock_inverted="false" is_slew_rate="false" tied_option="none" ddio_type="none" drive_strength="1"/>
            <efxpt:output_enable_config name="ioGPIOB_OE[17]" is_register="false" clock_name="" is_clock_inverted="false"/>
        </efxpt:gpio>
        <efxpt:gpio name="ioGPIOB[18]" gpio_def="GPIOB_RXP10" mode="inout" bus_name="ioGPIOB" is_lvds_gpio="true" io_standard="3.3 V LVTTL / LVCMOS">
            <efxpt:input_config name="ioGPIOB_I[18]" name_ddio_lo="" conn_type="normal" is_register="false" clock_name="" is_clock_inverted="false" pull_option="weak pullup" is_schmitt_trigger="false" ddio_type="none"/>
            <efxpt:output_config name="ioGPIOB_O[18]" name_ddio_lo="" register_option="none" clock_name="" is_clock_inverted="false" is_slew_rate="false" tied_option="none" ddio_type="none" drive_strength="1"/>
            <efxpt:output_enable_config name="ioGPIOB_OE[18]" is_register="false" clock_name="" is_clock_inverted="false"/>
        </efxpt:gpio>
        <efxpt:gpio name="ioGPIOB[19]" gpio_def="GPIOB_RXN10" mode="inout" bus_name="ioGPIOB" is_lvds_gpio="true" io_standard="3.3 V LVTTL / LVCMOS">
            <efxpt:input_config name="ioGPIOB_I[19]" name_ddio_lo="" conn_type="normal" is_register="false" clock_name="" is_clock_inverted="false" pull_option="weak pullup" is_schmitt_trigger="false" ddio_type="none"/>
            <efxpt:output_config name="ioGPIOB_O[19]" name_ddio_lo="" register_option="none" clock_name="" is_clock_inverted="false" is_slew_rate="false" tied_option="none" ddio_type="none" drive_strength="1"/>
            <efxpt:output_enable_config name="ioGPIOB_OE[19]" is_register="false" clock_name="" is_clock_inverted="false"/>
        </efxpt:gpio>
        <efxpt:gpio name="ioGPIOB[1]" gpio_def="GPIOB_TXN00" mode="inout" bus_name="ioGPIOB" is_lvds_gpio="true" io_standard="3.3 V LVTTL / LVCMOS">
            <efxpt:input_config name="ioGPIOB_I[1]" name_ddio_lo="" conn_type="normal" is_register="false" clock_name="" is_clock_inverted="false" pull_option="weak pullup" is_schmitt_trigger="false" ddio_type="none"/>
            <efxpt:output_config name="ioGPIOB_O[1]" name_ddio_lo="" register_option="none" clock_name="" is_clock_inverted="false" is_slew_rate="false" tied_option="none" ddio_type="none" drive_strength="1"/>
            <efxpt:output_enable_config name="ioGPIOB_OE[1]" is_register="false" clock_name="" is_clock_inverted="false"/>
        </efxpt:gpio>
        <efxpt:gpio name="ioGPIOB[20]" gpio_def="GPIOB_RXN12" mode="inout" bus_name="ioGPIOB" is_lvds_gpio="true" io_standard="3.3 V LVTTL / LVCMOS">
            <efxpt:input_config name="ioGPIOB_I[20]" name_ddio_lo="" conn_type="normal" is_register="false" clock_name="" is_clock_inverted="false" pull_option="weak pullup" is_schmitt_trigger="false" ddio_type="none"/>
            <efxpt:output_config name="ioGPIOB_O[20]" name_ddio_lo="" register_option="none" clock_name="" is_clock_inverted="false" is_slew_rate="false" tied_option="none" ddio_type="none" drive_strength="1"/>
            <efxpt:output_enable_config name="ioGPIOB_OE[20]" is_register="false" clock_name="" is_clock_inverted="false"/>
        </efxpt:gpio>
        <efxpt:gpio name="ioGPIOB[21]" gpio_def="GPIOB_RXP12" mode="inout" bus_name="ioGPIOB" is_lvds_gpio="true" io_standard="3.3 V LVTTL / LVCMOS">
            <efxpt:input_config name="ioGPIOB_I[21]" name_ddio_lo="" conn_type="normal" is_register="false" clock_name="" is_clock_inverted="false" pull_option="weak pullup" is_schmitt_trigger="false" ddio_type="none"/>
            <efxpt:output_config name="ioGPIOB_O[21]" name_ddio_lo="" register_option="none" clock_name="" is_clock_inverted="false" is_slew_rate="false" tied_option="none" ddio_type="none" drive_strength="1"/>
            <efxpt:output_enable_config name="ioGPIOB_OE[21]" is_register="false" clock_name="" is_clock_inverted="false"/>
        </efxpt:gpio>
        <efxpt:gpio name="ioGPIOB[22]" gpio_def="GPIOB_CLKP0" mode="inout" bus_name="ioGPIOB" is_lvds_gpio="true" io_standard="3.3 V LVTTL / LVCMOS">
            <efxpt:input_config name="ioGPIOB_I[22]" name_ddio_lo="" conn_type="normal" is_register="false" clock_name="" is_clock_inverted="false" pull_option="weak pullup" is_schmitt_trigger="false" ddio_type="none"/>
            <efxpt:output_config name="ioGPIOB_O[22]" name_ddio_lo="" register_option="none" clock_name="" is_clock_inverted="false" is_slew_rate="false" tied_option="none" ddio_type="none" drive_strength="1"/>
            <efxpt:output_enable_config name="ioGPIOB_OE[22]" is_register="false" clock_name="" is_clock_inverted="false"/>
        </efxpt:gpio>
        <efxpt:gpio name="ioGPIOB[23]" gpio_def="GPIOB_CLKN0" mode="inout" bus_name="ioGPIOB" is_lvds_gpio="true" io_standard="3.3 V LVTTL / LVCMOS">
            <efxpt:input_config name="ioGPIOB_I[23]" name_ddio_lo="" conn_type="normal" is_register="false" clock_name="" is_clock_inverted="false" pull_option="weak pullup" is_schmitt_trigger="false" ddio_type="none"/>
            <efxpt:output_config name="ioGPIOB_O[23]" name_ddio_lo="" register_option="none" clock_name="" is_clock_inverted="false" is_slew_rate="false" tied_option="none" ddio_type="none" drive_strength="1"/>
            <efxpt:output_enable_config name="ioGPIOB_OE[23]" is_register="false" clock_name="" is_clock_inverted="false"/>
        </efxpt:gpio>
        <efxpt:gpio name="ioGPIOB[2]" gpio_def="GPIOB_TXP02" mode="inout" bus_name="ioGPIOB" is_lvds_gpio="true" io_standard="3.3 V LVTTL / LVCMOS">
            <efxpt:input_config name="ioGPIOB_I[2]" name_ddio_lo="" conn_type="normal" is_register="false" clock_name="" is_clock_inverted="false" pull_option="weak pullup" is_schmitt_trigger="false" ddio_type="none"/>
            <efxpt:output_config name="ioGPIOB_O[2]" name_ddio_lo="" register_option="none" clock_name="" is_clock_inverted="false" is_slew_rate="false" tied_option="none" ddio_type="none" drive_strength="1"/>
            <efxpt:output_enable_config name="ioGPIOB_OE[2]" is_register="false" clock_name="" is_clock_inverted="false"/>
        </efxpt:gpio>
        <efxpt:gpio name="ioGPIOB[3]" gpio_def="GPIOB_TXN02" mode="inout" bus_name="ioGPIOB" is_lvds_gpio="true" io_standard="3.3 V LVTTL / LVCMOS">
            <efxpt:input_config name="ioGPIOB_I[3]" name_ddio_lo="" conn_type="normal" is_register="false" clock_name="" is_clock_inverted="false" pull_option="weak pullup" is_schmitt_trigger="false" ddio_type="none"/>
            <efxpt:output_config name="ioGPIOB_O[3]" name_ddio_lo="" register_option="none" clock_name="" is_clock_inverted="false" is_slew_rate="false" tied_option="none" ddio_type="none" drive_strength="1"/>
            <efxpt:output_enable_config name="ioGPIOB_OE[3]" is_register="false" clock_name="" is_clock_inverted="false"/>
        </efxpt:gpio>
        <efxpt:gpio name="ioGPIOB[4]" gpio_def="GPIOB_TXP04" mode="inout" bus_name="ioGPIOB" is_lvds_gpio="true" io_standard="3.3 V LVTTL / LVCMOS">
            <efxpt:input_config name="ioGPIOB_I[4]" name_ddio_lo="" conn_type="normal" is_register="false" clock_name="" is_clock_inverted="false" pull_option="weak pullup" is_schmitt_trigger="false" ddio_type="none"/>
            <efxpt:output_config name="ioGPIOB_O[4]" name_ddio_lo="" register_option="none" clock_name="" is_clock_inverted="false" is_slew_rate="false" tied_option="none" ddio_type="none" drive_strength="1"/>
            <efxpt:output_enable_config name="ioGPIOB_OE[4]" is_register="false" clock_name="" is_clock_inverted="false"/>
        </efxpt:gpio>
        <efxpt:gpio name="ioGPIOB[5]" gpio_def="GPIOB_TXN04" mode="inout" bus_name="ioGPIOB" is_lvds_gpio="true" io_standard="3.3 V LVTTL / LVCMOS">
            <efxpt:input_config name="ioGPIOB_I[5]" name_ddio_lo="" conn_type="normal" is_register="false" clock_name="" is_clock_inverted="false" pull_option="weak pullup" is_schmitt_trigger="false" ddio_type="none"/>
            <efxpt:output_config name="ioGPIOB_O[5]" name_ddio_lo="" register_option="none" clock_name="" is_clock_inverted="false" is_slew_rate="false" tied_option="none" ddio_type="none" drive_strength="1"/>
            <efxpt:output_enable_config name="ioGPIOB_OE[5]" is_register="false" clock_name="" is_clock_inverted="false"/>
        </efxpt:gpio>
        <efxpt:gpio name="ioGPIOB[6]" gpio_def="GPIOB_TXP06" mode="inout" bus_name="ioGPIOB" is_lvds_gpio="true" io_standard="3.3 V LVTTL / LVCMOS">
            <efxpt:input_config name="ioGPIOB_I[6]" name_ddio_lo="" conn_type="normal" is_register="false" clock_name="" is_clock_inverted="false" pull_option="weak pullup" is_schmitt_trigger="false" ddio_type="none"/>
            <efxpt:output_config name="ioGPIOB_O[6]" name_ddio_lo="" register_option="none" clock_name="" is_clock_inverted="false" is_slew_rate="false" tied_option="none" ddio_type="none" drive_strength="1"/>
            <efxpt:output_enable_config name="ioGPIOB_OE[6]" is_register="false" clock_name="" is_clock_inverted="false"/>
        </efxpt:gpio>
        <efxpt:gpio name="ioGPIOB[7]" gpio_def="GPIOB_TXN06" mode="inout" bus_name="ioGPIOB" is_lvds_gpio="true" io_standard="3.3 V LVTTL / LVCMOS">
            <efxpt:input_config name="ioGPIOB_I[7]" name_ddio_lo="" conn_type="normal" is_register="false" clock_name="" is_clock_inverted="false" pull_option="weak pullup" is_schmitt_trigger="false" ddio_type="none"/>
            <efxpt:output_config name="ioGPIOB_O[7]" name_ddio_lo="" register_option="none" clock_name="" is_clock_inverted="false" is_slew_rate="false" tied_option="none" ddio_type="none" drive_strength="1"/>
            <efxpt:output_enable_config name="ioGPIOB_OE[7]" is_register="false" clock_name="" is_clock_inverted="false"/>
        </efxpt:gpio>
        <efxpt:gpio name="ioGPIOB[8]" gpio_def="GPIOB_TXP09" mode="inout" bus_name="ioGPIOB" is_lvds_gpio="true" io_standard="3.3 V LVTTL / LVCMOS">
            <efxpt:input_config name="ioGPIOB_I[8]" name_ddio_lo="" conn_type="normal" is_register="false" clock_name="" is_clock_inverted="false" pull_option="weak pullup" is_schmitt_trigger="false" ddio_type="none"/>
            <efxpt:output_config name="ioGPIOB_O[8]" name_ddio_lo="" register_option="none" clock_name="" is_clock_inverted="false" is_slew_rate="false" tied_option="none" ddio_type="none" drive_strength="1"/>
            <efxpt:output_enable_config name="ioGPIOB_OE[8]" is_register="false" clock_name="" is_clock_inverted="false"/>
        </efxpt:gpio>
        <efxpt:gpio name="ioGPIOB[9]" gpio_def="GPIOB_TXN09" mode="inout" bus_name="ioGPIOB" is_lvds_gpio="true" io_standard="3.3 V LVTTL / LVCMOS">
            <efxpt:input_config name="ioGPIOB_I[9]" name_ddio_lo="" conn_type="normal" is_register="false" clock_name="" is_clock_inverted="false" pull_option="weak pullup" is_schmitt_trigger="false" ddio_type="none"/>
            <efxpt:output_config name="ioGPIOB_O[9]" name_ddio_lo="" register_option="none" clock_name="" is_clock_inverted="false" is_slew_rate="false" tied_option="none" ddio_type="none" drive_strength="1"/>
            <efxpt:output_enable_config name="ioGPIOB_OE[9]" is_register="false" clock_name="" is_clock_inverted="false"/>
        </efxpt:gpio>
        <efxpt:gpio name="ioGPIOL[0]" gpio_def="GPIOL_21" mode="inout" bus_name="ioGPIOL" is_lvds_gpio="false" io_standard="3.3 V LVTTL / LVCMOS">
            <efxpt:input_config name="ioGPIOL_I[0]" name_ddio_lo="" conn_type="normal" is_register="false" clock_name="" is_clock_inverted="false" pull_option="weak pullup" is_schmitt_trigger="false" ddio_type="none"/>
            <efxpt:output_config name="ioGPIOL_O[0]" name_ddio_lo="" register_option="none" clock_name="" is_clock_inverted="false" is_slew_rate="true" tied_option="none" ddio_type="none" drive_strength="4"/>
            <efxpt:output_enable_config name="ioGPIOL_OE[0]" is_register="false" clock_name="" is_clock_inverted="false"/>
        </efxpt:gpio>
        <efxpt:gpio name="ioGPIOL[10]" gpio_def="GPIOL_65" mode="inout" bus_name="ioGPIOL" is_lvds_gpio="false" io_standard="3.3 V LVTTL / LVCMOS">
            <efxpt:input_config name="ioGPIOL_I[10]" name_ddio_lo="" conn_type="normal" is_register="false" clock_name="" is_clock_inverted="false" pull_option="weak pullup" is_schmitt_trigger="false" ddio_type="none"/>
            <efxpt:output_config name="ioGPIOL_O[10]" name_ddio_lo="" register_option="none" clock_name="" is_clock_inverted="false" is_slew_rate="true" tied_option="none" ddio_type="none" drive_strength="4"/>
            <efxpt:output_enable_config name="ioGPIOL_OE[10]" is_register="false" clock_name="" is_clock_inverted="false"/>
        </efxpt:gpio>
        <efxpt:gpio name="ioGPIOL[11]" gpio_def="GPIOL_67" mode="inout" bus_name="ioGPIOL" is_lvds_gpio="false" io_standard="3.3 V LVTTL / LVCMOS">
            <efxpt:input_config name="ioGPIOL_I[11]" name_ddio_lo="" conn_type="normal" is_register="false" clock_name="" is_clock_inverted="false" pull_option="weak pullup" is_schmitt_trigger="false" ddio_type="none"/>
            <efxpt:output_config name="ioGPIOL_O[11]" name_ddio_lo="" register_option="none" clock_name="" is_clock_inverted="false" is_slew_rate="true" tied_option="none" ddio_type="none" drive_strength="4"/>
            <efxpt:output_enable_config name="ioGPIOL_OE[11]" is_register="false" clock_name="" is_clock_inverted="false"/>
        </efxpt:gpio>
        <efxpt:gpio name="ioGPIOL[12]" gpio_def="GPIOL_68" mode="inout" bus_name="ioGPIOL" is_lvds_gpio="false" io_standard="3.3 V LVTTL / LVCMOS">
            <efxpt:input_config name="ioGPIOL_I[12]" name_ddio_lo="" conn_type="normal" is_register="false" clock_name="" is_clock_inverted="false" pull_option="weak pullup" is_schmitt_trigger="false" ddio_type="none"/>
            <efxpt:output_config name="ioGPIOL_O[12]" name_ddio_lo="" register_option="none" clock_name="" is_clock_inverted="false" is_slew_rate="true" tied_option="none" ddio_type="none" drive_strength="4"/>
            <efxpt:output_enable_config name="ioGPIOL_OE[12]" is_register="false" clock_name="" is_clock_inverted="false"/>
        </efxpt:gpio>
        <efxpt:gpio name="ioGPIOL[13]" gpio_def="GPIOL_72" mode="inout" bus_name="ioGPIOL" is_lvds_gpio="false" io_standard="3.3 V LVTTL / LVCMOS">
            <efxpt:input_config name="ioGPIOL_I[13]" name_ddio_lo="" conn_type="normal" is_register="false" clock_name="" is_clock_inverted="false" pull_option="weak pullup" is_schmitt_trigger="false" ddio_type="none"/>
            <efxpt:output_config name="ioGPIOL_O[13]" name_ddio_lo="" register_option="none" clock_name="" is_clock_inverted="false" is_slew_rate="true" tied_option="none" ddio_type="none" drive_strength="4"/>
            <efxpt:output_enable_config name="ioGPIOL_OE[13]" is_register="false" clock_name="" is_clock_inverted="false"/>
        </efxpt:gpio>
        <efxpt:gpio name="ioGPIOL[14]" gpio_def="GPIOL_73" mode="inout" bus_name="ioGPIOL" is_lvds_gpio="false" io_standard="3.3 V LVTTL / LVCMOS">
            <efxpt:input_config name="ioGPIOL_I[14]" name_ddio_lo="" conn_type="normal" is_register="false" clock_name="" is_clock_inverted="false" pull_option="weak pullup" is_schmitt_trigger="false" ddio_type="none"/>
            <efxpt:output_config name="ioGPIOL_O[14]" name_ddio_lo="" register_option="none" clock_name="" is_clock_inverted="false" is_slew_rate="true" tied_option="none" ddio_type="none" drive_strength="4"/>
            <efxpt:output_enable_config name="ioGPIOL_OE[14]" is_register="false" clock_name="" is_clock_inverted="false"/>
        </efxpt:gpio>
        <efxpt:gpio name="ioGPIOL[15]" gpio_def="GPIOL_74" mode="inout" bus_name="ioGPIOL" is_lvds_gpio="false" io_standard="3.3 V LVTTL / LVCMOS">
            <efxpt:input_config name="ioGPIOL_I[15]" name_ddio_lo="" conn_type="normal" is_register="false" clock_name="" is_clock_inverted="false" pull_option="weak pullup" is_schmitt_trigger="false" ddio_type="none"/>
            <efxpt:output_config name="ioGPIOL_O[15]" name_ddio_lo="" register_option="none" clock_name="" is_clock_inverted="false" is_slew_rate="true" tied_option="none" ddio_type="none" drive_strength="4"/>
            <efxpt:output_enable_config name="ioGPIOL_OE[15]" is_register="false" clock_name="" is_clock_inverted="false"/>
        </efxpt:gpio>
        <efxpt:gpio name="ioGPIOL[16]" gpio_def="GPIOL_75" mode="inout" bus_name="ioGPIOL" is_lvds_gpio="false" io_standard="3.3 V LVTTL / LVCMOS">
            <efxpt:input_config name="ioGPIOL_I[16]" name_ddio_lo="" conn_type="normal" is_register="false" clock_name="" is_clock_inverted="false" pull_option="weak pullup" is_schmitt_trigger="false" ddio_type="none"/>
            <efxpt:output_config name="ioGPIOL_O[16]" name_ddio_lo="" register_option="none" clock_name="" is_clock_inverted="false" is_slew_rate="true" tied_option="none" ddio_type="none" drive_strength="4"/>
            <efxpt:output_enable_config name="ioGPIOL_OE[16]" is_register="false" clock_name="" is_clock_inverted="false"/>
        </efxpt:gpio>
        <efxpt:gpio name="ioGPIOL[1]" gpio_def="GPIOL_20" mode="inout" bus_name="ioGPIOL" is_lvds_gpio="false" io_standard="3.3 V LVTTL / LVCMOS">
            <efxpt:input_config name="ioGPIOL_I[1]" name_ddio_lo="" conn_type="normal" is_register="false" clock_name="" is_clock_inverted="false" pull_option="weak pullup" is_schmitt_trigger="false" ddio_type="none"/>
            <efxpt:output_config name="ioGPIOL_O[1]" name_ddio_lo="" register_option="none" clock_name="" is_clock_inverted="false" is_slew_rate="true" tied_option="none" ddio_type="none" drive_strength="4"/>
            <efxpt:output_enable_config name="ioGPIOL_OE[1]" is_register="false" clock_name="" is_clock_inverted="false"/>
        </efxpt:gpio>
        <efxpt:gpio name="ioGPIOL[2]" gpio_def="GPIOL_13" mode="inout" bus_name="ioGPIOL" is_lvds_gpio="false" io_standard="3.3 V LVTTL / LVCMOS">
            <efxpt:input_config name="ioGPIOL_I[2]" name_ddio_lo="" conn_type="normal" is_register="false" clock_name="" is_clock_inverted="false" pull_option="weak pullup" is_schmitt_trigger="false" ddio_type="none"/>
            <efxpt:output_config name="ioGPIOL_O[2]" name_ddio_lo="" register_option="none" clock_name="" is_clock_inverted="false" is_slew_rate="true" tied_option="none" ddio_type="none" drive_strength="4"/>
            <efxpt:output_enable_config name="ioGPIOL_OE[2]" is_register="false" clock_name="" is_clock_inverted="false"/>
        </efxpt:gpio>
        <efxpt:gpio name="ioGPIOL[3]" gpio_def="GPIOL_12" mode="inout" bus_name="ioGPIOL" is_lvds_gpio="false" io_standard="3.3 V LVTTL / LVCMOS">
            <efxpt:input_config name="ioGPIOL_I[3]" name_ddio_lo="" conn_type="normal" is_register="false" clock_name="" is_clock_inverted="false" pull_option="weak pullup" is_schmitt_trigger="false" ddio_type="none"/>
            <efxpt:output_config name="ioGPIOL_O[3]" name_ddio_lo="" register_option="none" clock_name="" is_clock_inverted="false" is_slew_rate="true" tied_option="none" ddio_type="none" drive_strength="4"/>
            <efxpt:output_enable_config name="ioGPIOL_OE[3]" is_register="false" clock_name="" is_clock_inverted="false"/>
        </efxpt:gpio>
        <efxpt:gpio name="ioGPIOL[4]" gpio_def="GPIOL_40" mode="inout" bus_name="ioGPIOL" is_lvds_gpio="false" io_standard="3.3 V LVTTL / LVCMOS">
            <efxpt:input_config name="ioGPIOL_I[4]" name_ddio_lo="" conn_type="normal" is_register="false" clock_name="" is_clock_inverted="false" pull_option="weak pullup" is_schmitt_trigger="false" ddio_type="none"/>
            <efxpt:output_config name="ioGPIOL_O[4]" name_ddio_lo="" register_option="none" clock_name="" is_clock_inverted="false" is_slew_rate="true" tied_option="none" ddio_type="none" drive_strength="4"/>
            <efxpt:output_enable_config name="ioGPIOL_OE[4]" is_register="false" clock_name="" is_clock_inverted="false"/>
        </efxpt:gpio>
        <efxpt:gpio name="ioGPIOL[5]" gpio_def="GPIOL_46" mode="inout" bus_name="ioGPIOL" is_lvds_gpio="false" io_standard="3.3 V LVTTL / LVCMOS">
            <efxpt:input_config name="ioGPIOL_I[5]" name_ddio_lo="" conn_type="normal" is_register="false" clock_name="" is_clock_inverted="false" pull_option="weak pullup" is_schmitt_trigger="false" ddio_type="none"/>
            <efxpt:output_config name="ioGPIOL_O[5]" name_ddio_lo="" register_option="none" clock_name="" is_clock_inverted="false" is_slew_rate="true" tied_option="none" ddio_type="none" drive_strength="4"/>
            <efxpt:output_enable_config name="ioGPIOL_OE[5]" is_register="false" clock_name="" is_clock_inverted="false"/>
        </efxpt:gpio>
        <efxpt:gpio name="ioGPIOL[6]" gpio_def="GPIOL_54" mode="inout" bus_name="ioGPIOL" is_lvds_gpio="false" io_standard="3.3 V LVTTL / LVCMOS">
            <efxpt:input_config name="ioGPIOL_I[6]" name_ddio_lo="" conn_type="normal" is_register="false" clock_name="" is_clock_inverted="false" pull_option="weak pullup" is_schmitt_trigger="false" ddio_type="none"/>
            <efxpt:output_config name="ioGPIOL_O[6]" name_ddio_lo="" register_option="none" clock_name="" is_clock_inverted="false" is_slew_rate="true" tied_option="none" ddio_type="none" drive_strength="4"/>
            <efxpt:output_enable_config name="ioGPIOL_OE[6]" is_register="false" clock_name="" is_clock_inverted="false"/>
        </efxpt:gpio>
        <efxpt:gpio name="ioGPIOL[7]" gpio_def="GPIOL_53" mode="inout" bus_name="ioGPIOL" is_lvds_gpio="false" io_standard="3.3 V LVTTL / LVCMOS">
            <efxpt:input_config name="ioGPIOL_I[7]" name_ddio_lo="" conn_type="normal" is_register="false" clock_name="" is_clock_inverted="false" pull_option="weak pullup" is_schmitt_trigger="false" ddio_type="none"/>
            <efxpt:output_config name="ioGPIOL_O[7]" name_ddio_lo="" register_option="none" clock_name="" is_clock_inverted="false" is_slew_rate="true" tied_option="none" ddio_type="none" drive_strength="4"/>
            <efxpt:output_enable_config name="ioGPIOL_OE[7]" is_register="false" clock_name="" is_clock_inverted="false"/>
        </efxpt:gpio>
        <efxpt:gpio name="ioGPIOL[8]" gpio_def="GPIOL_64" mode="inout" bus_name="ioGPIOL" is_lvds_gpio="false" io_standard="3.3 V LVTTL / LVCMOS">
            <efxpt:input_config name="ioGPIOL_I[8]" name_ddio_lo="" conn_type="normal" is_register="false" clock_name="" is_clock_inverted="false" pull_option="weak pullup" is_schmitt_trigger="false" ddio_type="none"/>
            <efxpt:output_config name="ioGPIOL_O[8]" name_ddio_lo="" register_option="none" clock_name="" is_clock_inverted="false" is_slew_rate="true" tied_option="none" ddio_type="none" drive_strength="4"/>
            <efxpt:output_enable_config name="ioGPIOL_OE[8]" is_register="false" clock_name="" is_clock_inverted="false"/>
        </efxpt:gpio>
        <efxpt:gpio name="ioGPIOL[9]" gpio_def="GPIOL_66" mode="inout" bus_name="ioGPIOL" is_lvds_gpio="false" io_standard="3.3 V LVTTL / LVCMOS">
            <efxpt:input_config name="ioGPIOL_I[9]" name_ddio_lo="" conn_type="normal" is_register="false" clock_name="" is_clock_inverted="false" pull_option="weak pullup" is_schmitt_trigger="false" ddio_type="none"/>
            <efxpt:output_config name="ioGPIOL_O[9]" name_ddio_lo="" register_option="none" clock_name="" is_clock_inverted="false" is_slew_rate="true" tied_option="none" ddio_type="none" drive_strength="4"/>
            <efxpt:output_enable_config name="ioGPIOL_OE[9]" is_register="false" clock_name="" is_clock_inverted="false"/>
        </efxpt:gpio>
        <efxpt:gpio name="ioGPIOR[0]" gpio_def="GPIOR_116" mode="inout" bus_name="ioGPIOR" is_lvds_gpio="false" io_standard="3.3 V LVTTL / LVCMOS">
            <efxpt:input_config name="ioGPIOR_I[0]" name_ddio_lo="" conn_type="normal" is_register="false" clock_name="" is_clock_inverted="false" pull_option="weak pullup" is_schmitt_trigger="false" ddio_type="none"/>
            <efxpt:output_config name="ioGPIOR_O[0]" name_ddio_lo="" register_option="none" clock_name="" is_clock_inverted="false" is_slew_rate="true" tied_option="none" ddio_type="none" drive_strength="4"/>
            <efxpt:output_enable_config name="ioGPIOR_OE[0]" is_register="false" clock_name="" is_clock_inverted="false"/>
        </efxpt:gpio>
        <efxpt:gpio name="ioGPIOR[10]" gpio_def="GPIOR_138" mode="inout" bus_name="ioGPIOR" is_lvds_gpio="false" io_standard="3.3 V LVTTL / LVCMOS">
            <efxpt:input_config name="ioGPIOR_I[10]" name_ddio_lo="" conn_type="normal" is_register="false" clock_name="" is_clock_inverted="false" pull_option="weak pullup" is_schmitt_trigger="false" ddio_type="none"/>
            <efxpt:output_config name="ioGPIOR_O[10]" name_ddio_lo="" register_option="none" clock_name="" is_clock_inverted="false" is_slew_rate="true" tied_option="none" ddio_type="none" drive_strength="4"/>
            <efxpt:output_enable_config name="ioGPIOR_OE[10]" is_register="false" clock_name="" is_clock_inverted="false"/>
        </efxpt:gpio>
        <efxpt:gpio name="ioGPIOR[11]" gpio_def="GPIOR_139" mode="inout" bus_name="ioGPIOR" is_lvds_gpio="false" io_standard="3.3 V LVTTL / LVCMOS">
            <efxpt:input_config name="ioGPIOR_I[11]" name_ddio_lo="" conn_type="normal" is_register="false" clock_name="" is_clock_inverted="false" pull_option="weak pullup" is_schmitt_trigger="false" ddio_type="none"/>
            <efxpt:output_config name="ioGPIOR_O[11]" name_ddio_lo="" register_option="none" clock_name="" is_clock_inverted="false" is_slew_rate="true" tied_option="none" ddio_type="none" drive_strength="4"/>
            <efxpt:output_enable_config name="ioGPIOR_OE[11]" is_register="false" clock_name="" is_clock_inverted="false"/>
        </efxpt:gpio>
        <efxpt:gpio name="ioGPIOR[12]" gpio_def="GPIOR_154" mode="inout" bus_name="ioGPIOR" is_lvds_gpio="false" io_standard="3.3 V LVTTL / LVCMOS">
            <efxpt:input_config name="ioGPIOR_I[12]" name_ddio_lo="" conn_type="normal" is_register="false" clock_name="" is_clock_inverted="false" pull_option="weak pullup" is_schmitt_trigger="false" ddio_type="none"/>
            <efxpt:output_config name="ioGPIOR_O[12]" name_ddio_lo="" register_option="none" clock_name="" is_clock_inverted="false" is_slew_rate="true" tied_option="none" ddio_type="none" drive_strength="4"/>
            <efxpt:output_enable_config name="ioGPIOR_OE[12]" is_register="false" clock_name="" is_clock_inverted="false"/>
        </efxpt:gpio>
        <efxpt:gpio name="ioGPIOR[13]" gpio_def="GPIOR_155" mode="inout" bus_name="ioGPIOR" is_lvds_gpio="false" io_standard="3.3 V LVTTL / LVCMOS">
            <efxpt:input_config name="ioGPIOR_I[13]" name_ddio_lo="" conn_type="normal" is_register="false" clock_name="" is_clock_inverted="false" pull_option="weak pullup" is_schmitt_trigger="false" ddio_type="none"/>
            <efxpt:output_config name="ioGPIOR_O[13]" name_ddio_lo="" register_option="none" clock_name="" is_clock_inverted="false" is_slew_rate="true" tied_option="none" ddio_type="none" drive_strength="4"/>
            <efxpt:output_enable_config name="ioGPIOR_OE[13]" is_register="false" clock_name="" is_clock_inverted="false"/>
        </efxpt:gpio>
        <efxpt:gpio name="ioGPIOR[14]" gpio_def="GPIOR_105" mode="inout" bus_name="ioGPIOR" is_lvds_gpio="false" io_standard="3.3 V LVTTL / LVCMOS">
            <efxpt:input_config name="ioGPIOR_I[14]" name_ddio_lo="" conn_type="normal" is_register="false" clock_name="" is_clock_inverted="false" pull_option="weak pullup" is_schmitt_trigger="false" ddio_type="none"/>
            <efxpt:output_config name="ioGPIOR_O[14]" name_ddio_lo="" register_option="none" clock_name="" is_clock_inverted="false" is_slew_rate="true" tied_option="none" ddio_type="none" drive_strength="4"/>
            <efxpt:output_enable_config name="ioGPIOR_OE[14]" is_register="false" clock_name="" is_clock_inverted="false"/>
        </efxpt:gpio>
        <efxpt:gpio name="ioGPIOR[15]" gpio_def="GPIOR_78" mode="inout" bus_name="ioGPIOR" is_lvds_gpio="false" io_standard="3.3 V LVTTL / LVCMOS">
            <efxpt:input_config name="ioGPIOR_I[15]" name_ddio_lo="" conn_type="normal" is_register="false" clock_name="" is_clock_inverted="false" pull_option="weak pullup" is_schmitt_trigger="false" ddio_type="none"/>
            <efxpt:output_config name="ioGPIOR_O[15]" name_ddio_lo="" register_option="none" clock_name="" is_clock_inverted="false" is_slew_rate="true" tied_option="none" ddio_type="none" drive_strength="4"/>
            <efxpt:output_enable_config name="ioGPIOR_OE[15]" is_register="false" clock_name="" is_clock_inverted="false"/>
        </efxpt:gpio>
        <efxpt:gpio name="ioGPIOR[16]" gpio_def="GPIOR_76" mode="inout" bus_name="ioGPIOR" is_lvds_gpio="false" io_standard="3.3 V LVTTL / LVCMOS">
            <efxpt:input_config name="ioGPIOR_I[16]" name_ddio_lo="" conn_type="normal" is_register="false" clock_name="" is_clock_inverted="false" pull_option="weak pullup" is_schmitt_trigger="false" ddio_type="none"/>
            <efxpt:output_config name="ioGPIOR_O[16]" name_ddio_lo="" register_option="none" clock_name="" is_clock_inverted="false" is_slew_rate="true" tied_option="none" ddio_type="none" drive_strength="4"/>
            <efxpt:output_enable_config name="ioGPIOR_OE[16]" is_register="false" clock_name="" is_clock_inverted="false"/>
        </efxpt:gpio>
        <efxpt:gpio name="ioGPIOR[17]" gpio_def="GPIOR_158" mode="inout" bus_name="ioGPIOR" is_lvds_gpio="false" io_standard="3.3 V LVTTL / LVCMOS">
            <efxpt:input_config name="ioGPIOR_I[17]" name_ddio_lo="" conn_type="normal" is_register="false" clock_name="" is_clock_inverted="false" pull_option="weak pullup" is_schmitt_trigger="false" ddio_type="none"/>
            <efxpt:output_config name="ioGPIOR_O[17]" name_ddio_lo="" register_option="none" clock_name="" is_clock_inverted="false" is_slew_rate="true" tied_option="none" ddio_type="none" drive_strength="4"/>
            <efxpt:output_enable_config name="ioGPIOR_OE[17]" is_register="false" clock_name="" is_clock_inverted="false"/>
        </efxpt:gpio>
        <efxpt:gpio name="ioGPIOR[18]" gpio_def="GPIOR_77" mode="inout" bus_name="ioGPIOR" is_lvds_gpio="false" io_standard="3.3 V LVTTL / LVCMOS">
            <efxpt:input_config name="ioGPIOR_I[18]" name_ddio_lo="" conn_type="normal" is_register="false" clock_name="" is_clock_inverted="false" pull_option="weak pullup" is_schmitt_trigger="false" ddio_type="none"/>
            <efxpt:output_config name="ioGPIOR_O[18]" name_ddio_lo="" register_option="none" clock_name="" is_clock_inverted="false" is_slew_rate="true" tied_option="none" ddio_type="none" drive_strength="4"/>
            <efxpt:output_enable_config name="ioGPIOR_OE[18]" is_register="false" clock_name="" is_clock_inverted="false"/>
        </efxpt:gpio>
        <efxpt:gpio name="ioGPIOR[19]" gpio_def="GPIOR_125" mode="inout" bus_name="ioGPIOR" is_lvds_gpio="false" io_standard="3.3 V LVTTL / LVCMOS">
            <efxpt:input_config name="ioGPIOR_I[19]" name_ddio_lo="" conn_type="normal" is_register="false" clock_name="" is_clock_inverted="false" pull_option="weak pullup" is_schmitt_trigger="false" ddio_type="none"/>
            <efxpt:output_config name="ioGPIOR_O[19]" name_ddio_lo="" register_option="none" clock_name="" is_clock_inverted="false" is_slew_rate="true" tied_option="none" ddio_type="none" drive_strength="4"/>
            <efxpt:output_enable_config name="ioGPIOR_OE[19]" is_register="false" clock_name="" is_clock_inverted="false"/>
        </efxpt:gpio>
        <efxpt:gpio name="ioGPIOR[1]" gpio_def="GPIOR_117" mode="inout" bus_name="ioGPIOR" is_lvds_gpio="false" io_standard="3.3 V LVTTL / LVCMOS">
            <efxpt:input_config name="ioGPIOR_I[1]" name_ddio_lo="" conn_type="normal" is_register="false" clock_name="" is_clock_inverted="false" pull_option="weak pullup" is_schmitt_trigger="false" ddio_type="none"/>
            <efxpt:output_config name="ioGPIOR_O[1]" name_ddio_lo="" register_option="none" clock_name="" is_clock_inverted="false" is_slew_rate="true" tied_option="none" ddio_type="none" drive_strength="4"/>
            <efxpt:output_enable_config name="ioGPIOR_OE[1]" is_register="false" clock_name="" is_clock_inverted="false"/>
        </efxpt:gpio>
        <efxpt:gpio name="ioGPIOR[20]" gpio_def="GPIOR_112" mode="inout" bus_name="ioGPIOR" is_lvds_gpio="false" io_standard="3.3 V LVTTL / LVCMOS">
            <efxpt:input_config name="ioGPIOR_I[20]" name_ddio_lo="" conn_type="normal" is_register="false" clock_name="" is_clock_inverted="false" pull_option="weak pullup" is_schmitt_trigger="false" ddio_type="none"/>
            <efxpt:output_config name="ioGPIOR_O[20]" name_ddio_lo="" register_option="none" clock_name="" is_clock_inverted="false" is_slew_rate="true" tied_option="none" ddio_type="none" drive_strength="4"/>
            <efxpt:output_enable_config name="ioGPIOR_OE[20]" is_register="false" clock_name="" is_clock_inverted="false"/>
        </efxpt:gpio>
        <efxpt:gpio name="ioGPIOR[2]" gpio_def="GPIOR_122" mode="inout" bus_name="ioGPIOR" is_lvds_gpio="false" io_standard="3.3 V LVTTL / LVCMOS">
            <efxpt:input_config name="ioGPIOR_I[2]" name_ddio_lo="" conn_type="normal" is_register="false" clock_name="" is_clock_inverted="false" pull_option="weak pullup" is_schmitt_trigger="false" ddio_type="none"/>
            <efxpt:output_config name="ioGPIOR_O[2]" name_ddio_lo="" register_option="none" clock_name="" is_clock_inverted="false" is_slew_rate="true" tied_option="none" ddio_type="none" drive_strength="4"/>
            <efxpt:output_enable_config name="ioGPIOR_OE[2]" is_register="false" clock_name="" is_clock_inverted="false"/>
        </efxpt:gpio>
        <efxpt:gpio name="ioGPIOR[3]" gpio_def="GPIOR_123" mode="inout" bus_name="ioGPIOR" is_lvds_gpio="false" io_standard="3.3 V LVTTL / LVCMOS">
            <efxpt:input_config name="ioGPIOR_I[3]" name_ddio_lo="" conn_type="normal" is_register="false" clock_name="" is_clock_inverted="false" pull_option="weak pullup" is_schmitt_trigger="false" ddio_type="none"/>
            <efxpt:output_config name="ioGPIOR_O[3]" name_ddio_lo="" register_option="none" clock_name="" is_clock_inverted="false" is_slew_rate="true" tied_option="none" ddio_type="none" drive_strength="4"/>
            <efxpt:output_enable_config name="ioGPIOR_OE[3]" is_register="false" clock_name="" is_clock_inverted="false"/>
        </efxpt:gpio>
        <efxpt:gpio name="ioGPIOR[4]" gpio_def="GPIOR_128" mode="inout" bus_name="ioGPIOR" is_lvds_gpio="false" io_standard="3.3 V LVTTL / LVCMOS">
            <efxpt:input_config name="ioGPIOR_I[4]" name_ddio_lo="" conn_type="normal" is_register="false" clock_name="" is_clock_inverted="false" pull_option="weak pullup" is_schmitt_trigger="false" ddio_type="none"/>
            <efxpt:output_config name="ioGPIOR_O[4]" name_ddio_lo="" register_option="none" clock_name="" is_clock_inverted="false" is_slew_rate="true" tied_option="none" ddio_type="none" drive_strength="4"/>
            <efxpt:output_enable_config name="ioGPIOR_OE[4]" is_register="false" clock_name="" is_clock_inverted="false"/>
        </efxpt:gpio>
        <efxpt:gpio name="ioGPIOR[5]" gpio_def="GPIOR_129" mode="inout" bus_name="ioGPIOR" is_lvds_gpio="false" io_standard="3.3 V LVTTL / LVCMOS">
            <efxpt:input_config name="ioGPIOR_I[5]" name_ddio_lo="" conn_type="normal" is_register="false" clock_name="" is_clock_inverted="false" pull_option="weak pullup" is_schmitt_trigger="false" ddio_type="none"/>
            <efxpt:output_config name="ioGPIOR_O[5]" name_ddio_lo="" register_option="none" clock_name="" is_clock_inverted="false" is_slew_rate="true" tied_option="none" ddio_type="none" drive_strength="4"/>
            <efxpt:output_enable_config name="ioGPIOR_OE[5]" is_register="false" clock_name="" is_clock_inverted="false"/>
        </efxpt:gpio>
        <efxpt:gpio name="ioGPIOR[6]" gpio_def="GPIOR_132" mode="inout" bus_name="ioGPIOR" is_lvds_gpio="false" io_standard="3.3 V LVTTL / LVCMOS">
            <efxpt:input_config name="ioGPIOR_I[6]" name_ddio_lo="" conn_type="normal" is_register="false" clock_name="" is_clock_inverted="false" pull_option="weak pullup" is_schmitt_trigger="false" ddio_type="none"/>
            <efxpt:output_config name="ioGPIOR_O[6]" name_ddio_lo="" register_option="none" clock_name="" is_clock_inverted="false" is_slew_rate="true" tied_option="none" ddio_type="none" drive_strength="4"/>
            <efxpt:output_enable_config name="ioGPIOR_OE[6]" is_register="false" clock_name="" is_clock_inverted="false"/>
        </efxpt:gpio>
        <efxpt:gpio name="ioGPIOR[7]" gpio_def="GPIOR_133" mode="inout" bus_name="ioGPIOR" is_lvds_gpio="false" io_standard="3.3 V LVTTL / LVCMOS">
            <efxpt:input_config name="ioGPIOR_I[7]" name_ddio_lo="" conn_type="normal" is_register="false" clock_name="" is_clock_inverted="false" pull_option="weak pullup" is_schmitt_trigger="false" ddio_type="none"/>
            <efxpt:output_config name="ioGPIOR_O[7]" name_ddio_lo="" register_option="none" clock_name="" is_clock_inverted="false" is_slew_rate="true" tied_option="none" ddio_type="none" drive_strength="4"/>
            <efxpt:output_enable_config name="ioGPIOR_OE[7]" is_register="false" clock_name="" is_clock_inverted="false"/>
        </efxpt:gpio>
        <efxpt:gpio name="ioGPIOR[8]" gpio_def="GPIOR_135" mode="inout" bus_name="ioGPIOR" is_lvds_gpio="false" io_standard="3.3 V LVTTL / LVCMOS">
            <efxpt:input_config name="ioGPIOR_I[8]" name_ddio_lo="" conn_type="normal" is_register="false" clock_name="" is_clock_inverted="false" pull_option="weak pullup" is_schmitt_trigger="false" ddio_type="none"/>
            <efxpt:output_config name="ioGPIOR_O[8]" name_ddio_lo="" register_option="none" clock_name="" is_clock_inverted="false" is_slew_rate="true" tied_option="none" ddio_type="none" drive_strength="4"/>
            <efxpt:output_enable_config name="ioGPIOR_OE[8]" is_register="false" clock_name="" is_clock_inverted="false"/>
        </efxpt:gpio>
        <efxpt:gpio name="ioGPIOR[9]" gpio_def="GPIOR_136" mode="inout" bus_name="ioGPIOR" is_lvds_gpio="false" io_standard="3.3 V LVTTL / LVCMOS">
            <efxpt:input_config name="ioGPIOR_I[9]" name_ddio_lo="" conn_type="normal" is_register="false" clock_name="" is_clock_inverted="false" pull_option="weak pullup" is_schmitt_trigger="false" ddio_type="none"/>
            <efxpt:output_config name="ioGPIOR_O[9]" name_ddio_lo="" register_option="none" clock_name="" is_clock_inverted="false" is_slew_rate="true" tied_option="none" ddio_type="none" drive_strength="4"/>
            <efxpt:output_enable_config name="ioGPIOR_OE[9]" is_register="false" clock_name="" is_clock_inverted="false"/>
        </efxpt:gpio>
        <efxpt:gpio name="ioSRAMD[0]" gpio_def="GPIOR_86" mode="inout" bus_name="ioSRAMD" is_lvds_gpio="false" io_standard="3.3 V LVTTL / LVCMOS">
            <efxpt:input_config name="ioSRAMD_I[0]" name_ddio_lo="" conn_type="normal" is_register="false" clock_name="" is_clock_inverted="false" pull_option="weak pullup" is_schmitt_trigger="false" ddio_type="none"/>
            <efxpt:output_config name="ioSRAMD_O[0]" name_ddio_lo="" register_option="none" clock_name="" is_clock_inverted="false" is_slew_rate="true" tied_option="none" ddio_type="none" drive_strength="4"/>
            <efxpt:output_enable_config name="ioSRAMD_OE[0]" is_register="false" clock_name="" is_clock_inverted="false"/>
        </efxpt:gpio>
        <efxpt:gpio name="ioSRAMD[1]" gpio_def="GPIOR_84" mode="inout" bus_name="ioSRAMD" is_lvds_gpio="false" io_standard="3.3 V LVTTL / LVCMOS">
            <efxpt:input_config name="ioSRAMD_I[1]" name_ddio_lo="" conn_type="normal" is_register="false" clock_name="" is_clock_inverted="false" pull_option="weak pullup" is_schmitt_trigger="false" ddio_type="none"/>
            <efxpt:output_config name="ioSRAMD_O[1]" name_ddio_lo="" register_option="none" clock_name="" is_clock_inverted="false" is_slew_rate="true" tied_option="none" ddio_type="none" drive_strength="4"/>
            <efxpt:output_enable_config name="ioSRAMD_OE[1]" is_register="false" clock_name="" is_clock_inverted="false"/>
        </efxpt:gpio>
        <efxpt:gpio name="ioSRAMD[2]" gpio_def="GPIOR_104" mode="inout" bus_name="ioSRAMD" is_lvds_gpio="false" io_standard="3.3 V LVTTL / LVCMOS">
            <efxpt:input_config name="ioSRAMD_I[2]" name_ddio_lo="" conn_type="normal" is_register="false" clock_name="" is_clock_inverted="false" pull_option="weak pullup" is_schmitt_trigger="false" ddio_type="none"/>
            <efxpt:output_config name="ioSRAMD_O[2]" name_ddio_lo="" register_option="none" clock_name="" is_clock_inverted="false" is_slew_rate="true" tied_option="none" ddio_type="none" drive_strength="4"/>
            <efxpt:output_enable_config name="ioSRAMD_OE[2]" is_register="false" clock_name="" is_clock_inverted="false"/>
        </efxpt:gpio>
        <efxpt:gpio name="ioSRAMD[3]" gpio_def="GPIOR_95" mode="inout" bus_name="ioSRAMD" is_lvds_gpio="false" io_standard="3.3 V LVTTL / LVCMOS">
            <efxpt:input_config name="ioSRAMD_I[3]" name_ddio_lo="" conn_type="normal" is_register="false" clock_name="" is_clock_inverted="false" pull_option="weak pullup" is_schmitt_trigger="false" ddio_type="none"/>
            <efxpt:output_config name="ioSRAMD_O[3]" name_ddio_lo="" register_option="none" clock_name="" is_clock_inverted="false" is_slew_rate="true" tied_option="none" ddio_type="none" drive_strength="4"/>
            <efxpt:output_enable_config name="ioSRAMD_OE[3]" is_register="false" clock_name="" is_clock_inverted="false"/>
        </efxpt:gpio>
        <efxpt:gpio name="ioSRAMD[4]" gpio_def="GPIOR_94" mode="inout" bus_name="ioSRAMD" is_lvds_gpio="false" io_standard="3.3 V LVTTL / LVCMOS">
            <efxpt:input_config name="ioSRAMD_I[4]" name_ddio_lo="" conn_type="normal" is_register="false" clock_name="" is_clock_inverted="false" pull_option="weak pullup" is_schmitt_trigger="false" ddio_type="none"/>
            <efxpt:output_config name="ioSRAMD_O[4]" name_ddio_lo="" register_option="none" clock_name="" is_clock_inverted="false" is_slew_rate="true" tied_option="none" ddio_type="none" drive_strength="4"/>
            <efxpt:output_enable_config name="ioSRAMD_OE[4]" is_register="false" clock_name="" is_clock_inverted="false"/>
        </efxpt:gpio>
        <efxpt:gpio name="ioSRAMD[5]" gpio_def="GPIOR_88" mode="inout" bus_name="ioSRAMD" is_lvds_gpio="false" io_standard="3.3 V LVTTL / LVCMOS">
            <efxpt:input_config name="ioSRAMD_I[5]" name_ddio_lo="" conn_type="normal" is_register="false" clock_name="" is_clock_inverted="false" pull_option="weak pullup" is_schmitt_trigger="false" ddio_type="none"/>
            <efxpt:output_config name="ioSRAMD_O[5]" name_ddio_lo="" register_option="none" clock_name="" is_clock_inverted="false" is_slew_rate="true" tied_option="none" ddio_type="none" drive_strength="4"/>
            <efxpt:output_enable_config name="ioSRAMD_OE[5]" is_register="false" clock_name="" is_clock_inverted="false"/>
        </efxpt:gpio>
        <efxpt:gpio name="ioSRAMD[6]" gpio_def="GPIOR_87" mode="inout" bus_name="ioSRAMD" is_lvds_gpio="false" io_standard="3.3 V LVTTL / LVCMOS">
            <efxpt:input_config name="ioSRAMD_I[6]" name_ddio_lo="" conn_type="normal" is_register="false" clock_name="" is_clock_inverted="false" pull_option="weak pullup" is_schmitt_trigger="false" ddio_type="none"/>
            <efxpt:output_config name="ioSRAMD_O[6]" name_ddio_lo="" register_option="none" clock_name="" is_clock_inverted="false" is_slew_rate="true" tied_option="none" ddio_type="none" drive_strength="4"/>
            <efxpt:output_enable_config name="ioSRAMD_OE[6]" is_register="false" clock_name="" is_clock_inverted="false"/>
        </efxpt:gpio>
        <efxpt:gpio name="ioSRAMD[7]" gpio_def="GPIOR_85" mode="inout" bus_name="ioSRAMD" is_lvds_gpio="false" io_standard="3.3 V LVTTL / LVCMOS">
            <efxpt:input_config name="ioSRAMD_I[7]" name_ddio_lo="" conn_type="normal" is_register="false" clock_name="" is_clock_inverted="false" pull_option="weak pullup" is_schmitt_trigger="false" ddio_type="none"/>
            <efxpt:output_config name="ioSRAMD_O[7]" name_ddio_lo="" register_option="none" clock_name="" is_clock_inverted="false" is_slew_rate="true" tied_option="none" ddio_type="none" drive_strength="4"/>
            <efxpt:output_enable_config name="ioSRAMD_OE[7]" is_register="false" clock_name="" is_clock_inverted="false"/>
        </efxpt:gpio>
        <efxpt:gpio name="ioSRAM_RWDS" gpio_def="GPIOR_83" mode="inout" bus_name="" is_lvds_gpio="false" io_standard="3.3 V LVTTL / LVCMOS">
            <efxpt:input_config name="ioSRAM_RWDS_I" name_ddio_lo="" conn_type="normal" is_register="false" clock_name="" is_clock_inverted="false" pull_option="weak pullup" is_schmitt_trigger="false" ddio_type="none"/>
            <efxpt:output_config name="ioSRAM_RWDS_O" name_ddio_lo="" register_option="none" clock_name="" is_clock_inverted="false" is_slew_rate="false" tied_option="none" ddio_type="none" drive_strength="4"/>
            <efxpt:output_enable_config name="ioSRAM_RWDS_OE" is_register="false" clock_name="" is_clock_inverted="false"/>
        </efxpt:gpio>
        <efxpt:gpio name="oSRAM_nCE" gpio_def="GPIOR_80" mode="output" bus_name="" is_lvds_gpio="false" io_standard="3.3 V LVTTL / LVCMOS">
            <efxpt:output_config name="oSRAM_nCE" name_ddio_lo="" register_option="none" clock_name="" is_clock_inverted="false" is_slew_rate="true" tied_option="none" ddio_type="none" drive_strength="4"/>
        </efxpt:gpio>
        <efxpt:gpio name="oSRAM_nCLK" gpio_def="GPIOR_82" mode="output" bus_name="" is_lvds_gpio="false" io_standard="3.3 V LVTTL / LVCMOS">
            <efxpt:output_config name="oSRAM_nCLK" name_ddio_lo="" register_option="none" clock_name="" is_clock_inverted="false" is_slew_rate="true" tied_option="none" ddio_type="none" drive_strength="4"/>
        </efxpt:gpio>
        <efxpt:gpio name="oSRAM_nRST" gpio_def="GPIOR_79" mode="output" bus_name="" is_lvds_gpio="false" io_standard="3.3 V LVTTL / LVCMOS">
            <efxpt:output_config name="oSRAM_nRST" name_ddio_lo="" register_option="none" clock_name="" is_clock_inverted="false" is_slew_rate="true" tied_option="none" ddio_type="none" drive_strength="4"/>
        </efxpt:gpio>
        <efxpt:gpio name="oSRAM_pCLK" gpio_def="GPIOR_81" mode="output" bus_name="" is_lvds_gpio="false" io_standard="3.3 V LVTTL / LVCMOS">
            <efxpt:output_config name="oSRAM_pCLK" name_ddio_lo="" register_option="none" clock_name="" is_clock_inverted="false" is_slew_rate="true" tied_option="none" ddio_type="none" drive_strength="4"/>
        </efxpt:gpio>
        <efxpt:gpio name="oUSB_TX" gpio_def="GPIOB_RXN07" mode="output" bus_name="" is_lvds_gpio="true" io_standard="3.3 V LVTTL / LVCMOS">
            <efxpt:output_config name="oUSB_TX" name_ddio_lo="" register_option="none" clock_name="" is_clock_inverted="false" is_slew_rate="false" tied_option="none" ddio_type="none" drive_strength="1"/>
        </efxpt:gpio>
        <efxpt:global_unused_config state="input with weak pullup"/>
        <efxpt:bus name="ioGPIOB" mode="inout" msb="23" lsb="0"/>
        <efxpt:bus name="ioGPIOL" mode="inout" msb="16" lsb="0"/>
        <efxpt:bus name="ioSRAMD" mode="inout" msb="7" lsb="0"/>
        <efxpt:bus name="ioGPIOR" mode="inout" msb="20" lsb="0"/>
    </efxpt:gpio_info>
    <efxpt:pll_info>
        <efxpt:pll name="PLL_BR0" pll_def="PLL_BR0" ref_clock_name="" ref_clock_freq="25.0000" multiplier="4" pre_divider="1" post_divider="4" reset_name="PLL_BR0_RSTN" locked_name="PLL_BR0_LOCKED" is_ipfrz="false" is_bypass_lock="true">
            <efxpt:output_clock name="iSCLK" number="0" out_divider="9" adv_out_phase_shift="0"/>
            <efxpt:adv_prop ref_clock_mode="external" ref_clock1_name="" ext_ref_clock_id="3" clksel_name="" feedback_clock_name="iSCLK" feedback_mode="core"/>
        </efxpt:pll>
        <efxpt:pll name="PLL_TL0" pll_def="PLL_TL0" ref_clock_name="iSCLK" ref_clock_freq="100.0000" multiplier="113" pre_divider="10" post_divider="2" reset_name="PLL_TL0_RSTN" locked_name="PLL_TL0_LOCKED" is_ipfrz="false" is_bypass_lock="true">
            <efxpt:output_clock name="iMCLK" number="0" out_divider="25" adv_out_phase_shift="0"/>
            <efxpt:adv_prop ref_clock_mode="core" ref_clock1_name="" ext_ref_clock_id="2" clksel_name="" feedback_clock_name="iMCLK" feedback_mode="internal"/>
        </efxpt:pll>
        <efxpt:pll name="PLL_TL1" pll_def="PLL_TL1" ref_clock_name="iSCLK" ref_clock_freq="100.0000" multiplier="153" pre_divider="10" post_divider="2" reset_name="PLL_TL1_RSTN" locked_name="PLL_TL1_LOCKED" is_ipfrz="false" is_bypass_lock="true">
            <efxpt:output_clock name="iVCLK" number="0" out_divider="85" adv_out_phase_shift="0"/>
            <efxpt:adv_prop ref_clock_mode="core" ref_clock1_name="" ext_ref_clock_id="2" clksel_name="" feedback_clock_name="iVCLK" feedback_mode="internal"/>
        </efxpt:pll>
    </efxpt:pll_info>
    <efxpt:lvds_info/>
    <efxpt:jtag_info>
        <efxpt:jtag name="jtag_inst1" jtag_def="JTAG_USER1">
            <efxpt:gen_pin>
                <efxpt:pin name="jtag_inst1_CAPTURE" type_name="CAPTURE" is_bus="false"/>
                <efxpt:pin name="jtag_inst1_DRCK" type_name="DRCK" is_bus="false"/>
                <efxpt:pin name="jtag_inst1_RESET" type_name="RESET" is_bus="false"/>
                <efxpt:pin name="jtag_inst1_RUNTEST" type_name="RUNTEST" is_bus="false"/>
                <efxpt:pin name="jtag_inst1_SEL" type_name="SEL" is_bus="false"/>
                <efxpt:pin name="jtag_inst1_SHIFT" type_name="SHIFT" is_bus="false"/>
                <efxpt:pin name="jtag_inst1_TCK" type_name="TCK" is_bus="false"/>
                <efxpt:pin name="jtag_inst1_TDI" type_name="TDI" is_bus="false"/>
                <efxpt:pin name="jtag_inst1_TMS" type_name="TMS" is_bus="false"/>
                <efxpt:pin name="jtag_inst1_UPDATE" type_name="UPDATE" is_bus="false"/>
                <efxpt:pin name="jtag_inst1_TDO" type_name="TDO" is_bus="false"/>
            </efxpt:gen_pin>
        </efxpt:jtag>
    </efxpt:jtag_info>
</efxpt:design_db>
